nrt_pytest_soft_asserts/__init__.py
nrt_pytest_soft_asserts/soft_asserts.py
nrt_pytest_soft_asserts-2.0.0.data/data/requirements.txt
nrt_pytest_soft_asserts-2.0.0.dist-info/licenses/LICENSE
nrt_pytest_soft_asserts-2.0.0.dist-info/METADATA
nrt_pytest_soft_asserts-2.0.0.dist-info/WHEEL
nrt_pytest_soft_asserts-2.0.0.dist-info/top_level.txt
nrt_pytest_soft_asserts-2.0.0.dist-info/RECORD
