Metadata-Version: 2.4
Name: nrt-pytest-soft-asserts
Version: 2.0.0
Summary: Soft asserts for pytest
Home-page: https://github.com/etuzon/python-nrt-pytest-soft-asserts
Author: Eyal Tuzon
Author-email: Eyal Tuzon <eyal.tuzon.dev@gmail.com>
License-Expression: MIT
Project-URL: Homepage, https://github.com/etuzon/python-nrt-pytest-soft-asserts
Project-URL: Bug Tracker, https://github.com/etuzon/python-nrt-pytest-soft-asserts/issues
Project-URL: documentation, https://github.com/etuzon/python-nrt-pytest-soft-asserts/wiki
Keywords: python,python3,python-3,pytest,soft,assert,asserts,assertion,assertions,soft-assert,soft-asserts,soft-assertion,soft-assertions,test,test-framework,unit-testing
Classifier: Programming Language :: Python :: 3
Classifier: Programming Language :: Python :: 3.8
Classifier: Programming Language :: Python :: 3.9
Classifier: Programming Language :: Python :: 3.10
Classifier: Programming Language :: Python :: 3.11
Classifier: Programming Language :: Python :: 3.12
Classifier: Programming Language :: Python :: 3.13
Classifier: Programming Language :: Python :: 3.14
Classifier: Operating System :: OS Independent
Classifier: Framework :: Pytest
Classifier: Topic :: Software Development :: Testing
Classifier: Topic :: Software Development :: Testing :: Unit
Classifier: Topic :: Software Development :: Libraries
Classifier: Development Status :: 5 - Production/Stable
Requires-Python: >=3.8
License-File: LICENSE
Requires-Dist: pytest>=7.0.1
Requires-Dist: zipp>=3.19.1
Dynamic: author
Dynamic: home-page
Dynamic: license-file
Dynamic: requires-dist
